{
  "version": 2,
  "checkedAt": "2026-07-23T18:39:28.954Z",
  "generatedAt": "2026-07-23T18:39:28.954Z",
  "lastSuccessfulAt": "2026-07-23T18:39:28.954Z",
  "status": "partial",
  "items": [
    {
      "title": "Burnham pauses early prison release scheme",
      "source": "BBC Politics",
      "url": "https://www.bbc.co.uk/news/articles/cx2lpjw516eo?at_medium=RSS&at_campaign=rss",
      "date": "2026-07-23T18:17:54.000Z",
      "country": "United Kingdom",
      "format": "News",
      "topic": "Politics",
      "kind": "News"
    },
    {
      "title": "For a 2nd time, House approves resolution to end the war in Iran in a rebuke to Trump",
      "source": "NPR News",
      "url": "https://www.npr.org/2026/07/23/nx-s1-5904515/congress-iran-war-powers-vote",
      "date": "2026-07-23T17:35:02.000Z",
      "country": "United States",
      "format": "News",
      "topic": "Politics",
      "kind": "News"
    },
    {
      "title": "Ex-rugby star Horgan sued for repossession of Dublin home",
      "source": "RTÉ News",
      "url": "https://www.rte.ie/news/courts/2026/0723/1584842-shane-horgan-courts/",
      "date": "2026-07-23T17:28:14.000Z",
      "country": "Ireland",
      "format": "News",
      "topic": "Politics",
      "kind": "News"
    },
    {
      "title": "Owner of Ontario bakery ‘panicked’ when Google's AI Overview mistakenly said they were shutting down",
      "source": "CBC News",
      "url": "https://www.cbc.ca/news/canada/kitchener-waterloo/anna-maes-millbank-not-closing-google-ai-overview-made-mistake-9.7281070?cmp=rss",
      "date": "2026-07-23T18:21:39.000Z",
      "country": "Canada",
      "format": "News",
      "topic": "Society",
      "kind": "News"
    },
    {
      "title": "Friday news quiz: World Cup winners, rock legends and Barnaby Joyce's dog",
      "source": "ABC News Australia",
      "url": "https://www.abc.net.au/news/2026-07-24/abc-news-quiz-july-24/106935898",
      "date": "2026-07-23T18:30:00.000Z",
      "country": "Australia",
      "format": "News",
      "topic": "Politics",
      "kind": "News"
    },
    {
      "title": "Long-time Wellington party flat shut down by council",
      "source": "RNZ News",
      "url": "https://www.rnz.co.nz/news/community/781441/long-time-wellington-party-flat-shut-down-by-council",
      "date": "2026-07-23T18:29:45.000Z",
      "country": "New Zealand",
      "format": "News",
      "topic": "Society",
      "kind": "News"
    },
    {
      "title": "Muttil tree-felling case: Kerala High Court upholds cheating charges against Augustine brothers",
      "source": "The Hindu",
      "url": "https://www.thehindu.com/news/national/kerala/muttil-tree-felling-case-kerala-high-court-upholds-cheating-charges-against-augustine-brothers/article71259436.ece",
      "date": "2026-07-23T18:35:14.000Z",
      "country": "India",
      "format": "News",
      "topic": "Politics",
      "kind": "News"
    },
    {
      "title": "Govender brothers murder trial hears allegations of domestic violence",
      "source": "SABC News",
      "url": "https://www.sabcnews.com/sabcnews/govender-brothers-murder-trial-hears-allegations-of-domestic-violence/",
      "date": "2026-07-23T17:55:58.000Z",
      "country": "South Africa",
      "format": "News",
      "topic": "Society",
      "kind": "News"
    },
    {
      "title": "Saudis must recognise Israel for nuclear deal, says Trump",
      "source": "BBC World",
      "url": "https://www.bbc.co.uk/news/articles/cwye71yq8wwo?at_medium=RSS&at_campaign=rss",
      "date": "2026-07-23T17:58:02.000Z",
      "country": "International",
      "format": "News",
      "topic": "International relations",
      "kind": "News"
    },
    {
      "title": "Co-operative Capital Bill [HL]",
      "source": "UK Parliament Bills",
      "url": "https://bills.parliament.uk/bills/4279",
      "date": "2026-07-23T16:49:46.000Z",
      "country": "United Kingdom",
      "format": "Primary source",
      "topic": "Politics",
      "kind": "Official"
    },
    {
      "title": "Houthis in Yemen target Saudi oil exports",
      "source": "BBC Global News Podcast",
      "url": "http://www.bbc.co.uk/programmes/p0p0hk2r",
      "date": "2026-07-23T15:49:00.000Z",
      "country": "International",
      "format": "Podcast",
      "topic": "International relations",
      "kind": "Podcast"
    },
    {
      "title": "Adolescence creator swaps therapy for chains in new movie",
      "source": "ABC News Australia",
      "url": "https://www.abc.net.au/news/2026-07-24/what-to-watch-in-cinemas-in-july/106940720",
      "date": "2026-07-23T18:30:00.000Z",
      "country": "Australia",
      "format": "News",
      "topic": "Politics",
      "kind": "News"
    },
    {
      "title": "Jantar Mantar protest LIVE: Government and CJP delegation have likely agreed to meet tomorrow, a government source says",
      "source": "The Hindu",
      "url": "https://www.thehindu.com/news/national/cjp-jantar-mantar-protest-live-updates-abhijeet-dipke-saurav-das-sonam-wangchuk-hunger-strike-dharmendra-pradhan-resignation/article71256169.ece",
      "date": "2026-07-23T18:29:39.000Z",
      "country": "India",
      "format": "News",
      "topic": "Politics",
      "kind": "News"
    },
    {
      "title": "Woman who almost died in Auckland swimming pool returns to thank her saviours",
      "source": "RNZ News",
      "url": "https://www.rnz.co.nz/news/community/781432/woman-who-almost-died-in-auckland-swimming-pool-returns-to-thank-her-saviours",
      "date": "2026-07-23T18:29:22.000Z",
      "country": "New Zealand",
      "format": "News",
      "topic": "Society",
      "kind": "News"
    },
    {
      "title": "Kerala High Court quashes sexual harassment case against Boby Chemmanur",
      "source": "The Hindu",
      "url": "https://www.thehindu.com/news/national/kerala/kerala-high-court-quashes-sexual-harassment-case-against-boby-chemmanur/article71259467.ece",
      "date": "2026-07-23T18:27:17.000Z",
      "country": "India",
      "format": "News",
      "topic": "Politics",
      "kind": "News"
    },
    {
      "title": "University of Toronto mathematician Jacob Tsimerman wins Fields Medal",
      "source": "CBC News",
      "url": "https://www.cbc.ca/news/science/fields-medal-jacob-tsimerman-9.7281134?cmp=rss",
      "date": "2026-07-23T18:14:07.000Z",
      "country": "Canada",
      "format": "News",
      "topic": "Society",
      "kind": "News"
    },
    {
      "title": "Kerala government reconstitutes prison advisory committees",
      "source": "The Hindu",
      "url": "https://www.thehindu.com/news/national/kerala/kerala-government-reconstitutes-prison-advisory-committees/article71258842.ece",
      "date": "2026-07-23T18:09:56.000Z",
      "country": "India",
      "format": "News",
      "topic": "Politics",
      "kind": "News"
    },
    {
      "title": "Delhi High Court notifies designated court to deal with criminal cases arising from exam paper leaks",
      "source": "The Hindu",
      "url": "https://www.thehindu.com/news/national/delhi-high-court-notifies-designated-court-to-deal-with-criminal-cases-arising-from-exam-paper-leaks/article71259539.ece",
      "date": "2026-07-23T18:08:29.000Z",
      "country": "India",
      "format": "News",
      "topic": "Politics",
      "kind": "News"
    },
    {
      "title": "AU distance education examination postponed to August 4 over State bandh",
      "source": "The Hindu",
      "url": "https://www.thehindu.com/news/national/andhra-pradesh/au-distance-education-examination-postponed-to-august-4-over-state-bandh/article71258934.ece",
      "date": "2026-07-23T18:04:57.000Z",
      "country": "India",
      "format": "News",
      "topic": "Politics",
      "kind": "News"
    },
    {
      "title": "Students stage protest against paper leaks, police action in Delhi",
      "source": "The Hindu",
      "url": "https://www.thehindu.com/news/national/andhra-pradesh/students-stage-protest-against-paper-leaks-police-action-in-delhi/article71259107.ece",
      "date": "2026-07-23T17:59:20.000Z",
      "country": "India",
      "format": "News",
      "topic": "Politics",
      "kind": "News"
    }
  ],
  "sources": {
    "attempted": 18,
    "successful": 17,
    "failed": 1,
    "failures": [
      {
        "source": "Mail & Guardian",
        "error": "HTTP 404"
      }
    ]
  }
}
